AUTHORS
LICENSE
MANIFEST.in
README.rst
setup.py
sickmuse/__init__.py
sickmuse/app.py
sickmuse/handlers.py
sickmuse.egg-info/PKG-INFO
sickmuse.egg-info/SOURCES.txt
sickmuse.egg-info/dependency_links.txt
sickmuse.egg-info/entry_points.txt
sickmuse.egg-info/not-zip-safe
sickmuse.egg-info/requires.txt
sickmuse.egg-info/top_level.txt
sickmuse/static/.bowerrc
sickmuse/static/component.json
sickmuse/static/favicon.ico
sickmuse/static/css/sickmuse.css
sickmuse/static/font/FontAwesome.otf
sickmuse/static/font/fontawesome-webfont.eot
sickmuse/static/font/fontawesome-webfont.svg
sickmuse/static/font/fontawesome-webfont.ttf
sickmuse/static/font/fontawesome-webfont.woff
sickmuse/static/img/logo.png
sickmuse/static/img/logo.svg
sickmuse/static/img/px_tile.png
sickmuse/static/js/sickmuse-built.js
sickmuse/static/js/sickmuse.js
sickmuse/static/js/models/host-plugin.js
sickmuse/static/js/views/plugin-graph.js
sickmuse/static/less/extensions.less
sickmuse/static/less/sickmuse.less
sickmuse/static/libs/backbone/LICENSE
sickmuse/static/libs/backbone/backbone.js
sickmuse/static/libs/bootstrap/LICENSE
sickmuse/static/libs/bootstrap/img/glyphicons-halflings-white.png
sickmuse/static/libs/bootstrap/img/glyphicons-halflings.png
sickmuse/static/libs/bootstrap/js/bootstrap-collapse.js
sickmuse/static/libs/bootstrap/js/bootstrap-scrollspy.js
sickmuse/static/libs/bootstrap/less/accordion.less
sickmuse/static/libs/bootstrap/less/alerts.less
sickmuse/static/libs/bootstrap/less/bootstrap.less
sickmuse/static/libs/bootstrap/less/breadcrumbs.less
sickmuse/static/libs/bootstrap/less/button-groups.less
sickmuse/static/libs/bootstrap/less/buttons.less
sickmuse/static/libs/bootstrap/less/carousel.less
sickmuse/static/libs/bootstrap/less/close.less
sickmuse/static/libs/bootstrap/less/code.less
sickmuse/static/libs/bootstrap/less/component-animations.less
sickmuse/static/libs/bootstrap/less/dropdowns.less
sickmuse/static/libs/bootstrap/less/forms.less
sickmuse/static/libs/bootstrap/less/grid.less
sickmuse/static/libs/bootstrap/less/hero-unit.less
sickmuse/static/libs/bootstrap/less/labels-badges.less
sickmuse/static/libs/bootstrap/less/layouts.less
sickmuse/static/libs/bootstrap/less/media.less
