Metadata-Version: 1.1
Name: sickmuse
Version: 0.2.0
Summary: A Collectd Frontend with heart.
Home-page: https://github.com/mlavin/sickmuse
Author: Mark Lavin
Author-email: markdlavin@gmail.com
License: BSD
Platform: UNKNOWN
Classifier: Development Status :: 4 - Beta
Classifier: License :: OSI Approved :: BSD License
Classifier: Operating System :: OS Independent
Classifier: Programming Language :: Python
Classifier: Programming Language :: Python :: 2.6
Classifier: Programming Language :: Python :: 2.7
Classifier: Topic :: Internet :: WWW/HTTP :: Dynamic Content
